ai_hedge_fund/__main__.py
ai_hedge_fund/backtester.py
ai_hedge_fund/py.typed
ai_hedge_fund/agents/ben_graham.py
ai_hedge_fund/agents/bill_ackman.py
ai_hedge_fund/agents/cathie_wood.py
ai_hedge_fund/agents/charlie_munger.py
ai_hedge_fund/agents/fundamentals.py
ai_hedge_fund/agents/michael_burry.py
ai_hedge_fund/agents/peter_lynch.py
ai_hedge_fund/agents/phil_fisher.py
ai_hedge_fund/agents/portfolio_manager.py
ai_hedge_fund/agents/risk_manager.py
ai_hedge_fund/agents/sentiment.py
ai_hedge_fund/agents/stanley_druckenmiller.py
ai_hedge_fund/agents/technicals.py
ai_hedge_fund/agents/valuation.py
ai_hedge_fund/agents/warren_buffett.py
ai_hedge_fund/data/cache.py
ai_hedge_fund/data/models.py
ai_hedge_fund/graph/state.py
ai_hedge_fund/llm/models.py
ai_hedge_fund/tools/api.py
ai_hedge_fund/utils/__init__.py
ai_hedge_fund/utils/analysts.py
ai_hedge_fund/utils/display.py
ai_hedge_fund/utils/docker.py
ai_hedge_fund/utils/llm.py
ai_hedge_fund/utils/ollama.py
ai_hedge_fund/utils/progress.py
ai_hedge_fund/utils/visualize.py
ahfu-0.2.0.dist-info/METADATA
ahfu-0.2.0.dist-info/WHEEL
ahfu-0.2.0.dist-info/entry_points.txt
ahfu-0.2.0.dist-info/licenses/LICENSE
ahfu-0.2.0.dist-info/RECORD
