Metadata-Version: 2.4
Name: ahfu
Version: 0.2.0
Summary: AI对冲基金项目-uv分支 , An AI-powered hedge fund that uses multiple agents to make trading decisions
Author-email: virattt <???@???.com>, LIghtJUNction <LIghtJUNction.me@gmail.com>
License-File: LICENSE
Requires-Python: >=3.13
Requires-Dist: click>=8.1.8
Requires-Dist: colorama>=0.4.6
Requires-Dist: langchain-anthropic>=0.3.12
Requires-Dist: langchain-deepseek>=0.1.3
Requires-Dist: langchain-google-genai>=2.1.3
Requires-Dist: langchain-groq>=0.3.2
Requires-Dist: langchain-ollama>=0.3.2
Requires-Dist: langchain-openai>=0.3.14
Requires-Dist: langchain>=0.3.24
Requires-Dist: langgraph>=0.3.34
Requires-Dist: matplotlib>=3.10.1
Requires-Dist: numpy>=2.2.5
Requires-Dist: pandas>=2.2.3
Requires-Dist: python-dotenv>=1.1.0
Requires-Dist: questionary>=2.1.0
Requires-Dist: rich>=14.0.0
Requires-Dist: tabulate>=0.9.0
Provides-Extra: dev
Requires-Dist: black>=25.1.0; extra == 'dev'
Requires-Dist: flake8>=7.2.0; extra == 'dev'
Requires-Dist: isort>=6.0.1; extra == 'dev'
Requires-Dist: pytest>=8.3.5; extra == 'dev'
